filemeta/__init__.py
filemeta/exif.py
filemeta/fsreaders.py
filemeta/listreaders.py
filemeta/mediainfo.py
filemeta/mp3.py
filemeta/py.typed
filemeta/utils.py
filemeta/data/exif-key-labels.json
filemeta/data/exif-value-labels.json
filemeta/data/mediainfo-fields.json
filemeta/data/mediainfo-types.json
filemeta-0.0.3.dist-info/LICENSE
filemeta-0.0.3.dist-info/METADATA
filemeta-0.0.3.dist-info/WHEEL
filemeta-0.0.3.dist-info/top_level.txt
filemeta-0.0.3.dist-info/zip-safe
filemeta-0.0.3.dist-info/RECORD
