Metadata-Version: 2.1
Name: filemeta
Version: 0.0.3
Summary: functions to read file meta information
Home-page: https://github.com/Dobatymo/filemeta
Author: Dobatymo
License: UNKNOWN
Platform: UNKNOWN
Classifier: Intended Audience :: Developers
Classifier: License :: OSI Approved :: ISC License (ISCL)
Classifier: Operating System :: OS Independent
Classifier: Programming Language :: Python :: 3
Requires-Python: >=3.7
Requires-Dist: bitstruct
Requires-Dist: fastcrc
Requires-Dist: genutility[json] >=0.0.102
Requires-Dist: importlib-resources
Requires-Dist: piexif
Requires-Dist: pymediainfo
Requires-Dist: requests
Requires-Dist: typing-extensions
